{
"meta":{"test_sets":[],"test_metrics":[],"learn_metrics":[{"best_value":"Min","name":"RMSE"}],"launch_mode":"Train","parameters":"","iteration_count":100,"learn_sets":["learn"],"name":"experiment"},
"iterations":[
{"learn":[14.005006],"iteration":0,"passed_time":0.001364517642,"remaining_time":0.1350872465},
{"learn":[13.14441192],"iteration":1,"passed_time":0.002646463353,"remaining_time":0.1296767043},
{"learn":[12.34258257],"iteration":2,"passed_time":0.003870029934,"remaining_time":0.1251309679},
{"learn":[11.64527793],"iteration":3,"passed_time":0.004832055682,"remaining_time":0.1159693364},
{"learn":[11.02766183],"iteration":4,"passed_time":0.006048539245,"remaining_time":0.1149222456},
{"learn":[10.43485794],"iteration":5,"passed_time":0.007254192045,"remaining_time":0.1136490087},
{"learn":[9.890641275],"iteration":6,"passed_time":0.00859076459,"remaining_time":0.1141344438},
{"learn":[9.492161212],"iteration":7,"passed_time":0.009850390917,"remaining_time":0.1132794956},
{"learn":[9.105082953],"iteration":8,"passed_time":0.01107478927,"remaining_time":0.1119784248},
{"learn":[8.674157135],"iteration":9,"passed_time":0.01226681097,"remaining_time":0.1104012987},
{"learn":[8.341743544],"iteration":10,"passed_time":0.01345567449,"remaining_time":0.1088686391},
{"learn":[8.049372916],"iteration":11,"passed_time":0.01468078852,"remaining_time":0.1076591158},
{"learn":[7.757318612],"iteration":12,"passed_time":0.0158562982,"remaining_time":0.1061152264},
{"learn":[7.522206899],"iteration":13,"passed_time":0.01704410051,"remaining_time":0.1046994745},
{"learn":[7.297756655],"iteration":14,"passed_time":0.01824102633,"remaining_time":0.1033658158},
{"learn":[7.088359431],"iteration":15,"passed_time":0.01951174155,"remaining_time":0.1024366431},
{"learn":[6.882113791],"iteration":16,"passed_time":0.0206969493,"remaining_time":0.1010498113},
{"learn":[6.704728832],"iteration":17,"passed_time":0.02189746261,"remaining_time":0.09975510743},
{"learn":[6.563881962],"iteration":18,"passed_time":0.02312804164,"remaining_time":0.09859849331},
{"learn":[6.418790279],"iteration":19,"passed_time":0.02437417481,"remaining_time":0.09749669925},
{"learn":[6.315756953],"iteration":20,"passed_time":0.02558442625,"remaining_time":0.09624617494},
{"learn":[6.210157751],"iteration":21,"passed_time":0.02677539082,"remaining_time":0.0949309311},
{"learn":[6.115058449],"iteration":22,"passed_time":0.02798177569,"remaining_time":0.09367811862},
{"learn":[6.014819884],"iteration":23,"passed_time":0.02919465082,"remaining_time":0.0924497276},
{"learn":[5.93117229],"iteration":24,"passed_time":0.03039588254,"remaining_time":0.09118764762},
{"learn":[5.844857622],"iteration":25,"passed_time":0.03160323029,"remaining_time":0.08994765545},
{"learn":[5.771145213],"iteration":26,"passed_time":0.03280688812,"remaining_time":0.08870010492},
{"learn":[5.704018229],"iteration":27,"passed_time":0.03459792702,"remaining_time":0.08896609804},
{"learn":[5.665806474],"iteration":28,"passed_time":0.0360291902,"remaining_time":0.0882093967},
{"learn":[5.616500369],"iteration":29,"passed_time":0.03754342595,"remaining_time":0.08760132721},
{"learn":[5.558023666],"iteration":30,"passed_time":0.03899298715,"remaining_time":0.08679084238},
{"learn":[5.510080976],"iteration":31,"passed_time":0.04037611786,"remaining_time":0.08579925046},
{"learn":[5.468747792],"iteration":32,"passed_time":0.04191791856,"remaining_time":0.08510607708},
{"learn":[5.429275534],"iteration":33,"passed_time":0.04338550281,"remaining_time":0.08421891723},
{"learn":[5.402117324],"iteration":34,"passed_time":0.0447894346,"remaining_time":0.08318037854},
{"learn":[5.367635151],"iteration":35,"passed_time":0.04632613769,"remaining_time":0.08235757811},
{"learn":[5.345181232],"iteration":36,"passed_time":0.04775554111,"remaining_time":0.08131348892},
{"learn":[5.319151269],"iteration":37,"passed_time":0.04911681362,"remaining_time":0.08013795907},
{"learn":[5.296134146],"iteration":38,"passed_time":0.05059527007,"remaining_time":0.07913619164},
{"learn":[5.269629003],"iteration":39,"passed_time":0.05201257891,"remaining_time":0.07801886837},
{"learn":[5.251147059],"iteration":40,"passed_time":0.05342565197,"remaining_time":0.07688081625},
{"learn":[5.248003302],"iteration":41,"passed_time":0.05406816021,"remaining_time":0.07466555457},
{"learn":[5.232376509],"iteration":42,"passed_time":0.0554243515,"remaining_time":0.0734694892},
{"learn":[5.213524255],"iteration":43,"passed_time":0.05678758302,"remaining_time":0.07227510566},
{"learn":[5.189691584],"iteration":44,"passed_time":0.05825219393,"remaining_time":0.07119712592},
{"learn":[5.166052198],"iteration":45,"passed_time":0.05971582557,"remaining_time":0.07010118654},
{"learn":[5.140406659],"iteration":46,"passed_time":0.06119909098,"remaining_time":0.06901174089},
{"learn":[5.118929684],"iteration":47,"passed_time":0.06270530177,"remaining_time":0.06793074358},
{"learn":[5.108792602],"iteration":48,"passed_time":0.06422030418,"remaining_time":0.06684154108},
{"learn":[5.098141225],"iteration":49,"passed_time":0.06566552079,"remaining_time":0.06566552079},
{"learn":[5.085926393],"iteration":50,"passed_time":0.06717278551,"remaining_time":0.06453855863},
{"learn":[5.067816804],"iteration":51,"passed_time":0.06857826201,"remaining_time":0.06330301109},
{"learn":[5.049834901],"iteration":52,"passed_time":0.070081896,"remaining_time":0.06214809645},
{"learn":[5.03838627],"iteration":53,"passed_time":0.07158423839,"remaining_time":0.06097916604},
{"learn":[5.033534248],"iteration":54,"passed_time":0.07251592389,"remaining_time":0.05933121046},
{"learn":[5.023726885],"iteration":55,"passed_time":0.07418489386,"remaining_time":0.05828813089},
{"learn":[5.01290392],"iteration":56,"passed_time":0.07568137881,"remaining_time":0.05709296998},
{"learn":[5.005569127],"iteration":57,"passed_time":0.07702072984,"remaining_time":0.05577363195},
{"learn":[4.989969032],"iteration":58,"passed_time":0.07852899751,"remaining_time":0.05457099827},
{"learn":[4.976762446],"iteration":59,"passed_time":0.07994416888,"remaining_time":0.05329611259},
{"learn":[4.967222715],"iteration":60,"passed_time":0.08137884155,"remaining_time":0.05202909542},
{"learn":[4.954407599],"iteration":61,"passed_time":0.08281234964,"remaining_time":0.05075595623},
{"learn":[4.942125056],"iteration":62,"passed_time":0.08417795583,"remaining_time":0.04943784707},
{"learn":[4.930230716],"iteration":63,"passed_time":0.08568665737,"remaining_time":0.04819874477},
{"learn":[4.921695642],"iteration":64,"passed_time":0.08713457188,"remaining_time":0.04691861563},
{"learn":[4.906405625],"iteration":65,"passed_time":0.08880848238,"remaining_time":0.04574982426},
{"learn":[4.894330248],"iteration":66,"passed_time":0.09021378861,"remaining_time":0.04443365708},
{"learn":[4.88211557],"iteration":67,"passed_time":0.09161754467,"remaining_time":0.04311413867},
{"learn":[4.877946398],"iteration":68,"passed_time":0.0932402706,"remaining_time":0.04189055636},
{"learn":[4.863182126],"iteration":69,"passed_time":0.09464598338,"remaining_time":0.04056256431},
{"learn":[4.84646533],"iteration":70,"passed_time":0.09607740682,"remaining_time":0.03924288447},
{"learn":[4.838014752],"iteration":71,"passed_time":0.09753551654,"remaining_time":0.03793047866},
{"learn":[4.82981137],"iteration":72,"passed_time":0.09898799281,"remaining_time":0.03661199734},
{"learn":[4.817094767],"iteration":73,"passed_time":0.1005258049,"remaining_time":0.03531987741},
{"learn":[4.808314151],"iteration":74,"passed_time":0.1020478776,"remaining_time":0.03401595921},
{"learn":[4.796235023],"iteration":75,"passed_time":0.1035090071,"remaining_time":0.03268705488},
{"learn":[4.784434534],"iteration":76,"passed_time":0.1048941451,"remaining_time":0.03133201736},
{"learn":[4.774402487],"iteration":77,"passed_time":0.1063290818,"remaining_time":0.02999025384},
{"learn":[4.76731896],"iteration":78,"passed_time":0.1077885177,"remaining_time":0.02865264395},
{"learn":[4.75934113],"iteration":79,"passed_time":0.1092096863,"remaining_time":0.02730242158},
{"learn":[4.754106378],"iteration":80,"passed_time":0.1107492061,"remaining_time":0.02597820884},
{"learn":[4.744002932],"iteration":81,"passed_time":0.1121915864,"remaining_time":0.02462742141},
{"learn":[4.731700554],"iteration":82,"passed_time":0.1135561856,"remaining_time":0.02325849584},
{"learn":[4.723284153],"iteration":83,"passed_time":0.1150146035,"remaining_time":0.02190754352},
{"learn":[4.712232782],"iteration":84,"passed_time":0.1165955006,"remaining_time":0.02057567657},
{"learn":[4.703046867],"iteration":85,"passed_time":0.1181328984,"remaining_time":0.01923093695},
{"learn":[4.698601855],"iteration":86,"passed_time":0.1195321678,"remaining_time":0.01786112852},
{"learn":[4.692429407],"iteration":87,"passed_time":0.1209328822,"remaining_time":0.01649084758},
{"learn":[4.675027364],"iteration":88,"passed_time":0.1224581673,"remaining_time":0.0151352791},
{"learn":[4.662368584],"iteration":89,"passed_time":0.1239035714,"remaining_time":0.01376706349},
{"learn":[4.646206172],"iteration":90,"passed_time":0.1252876414,"remaining_time":0.01239108541},
{"learn":[4.641245848],"iteration":91,"passed_time":0.1267504358,"remaining_time":0.01102177702},
{"learn":[4.633900435],"iteration":92,"passed_time":0.1281982342,"remaining_time":0.009649329456},
{"learn":[4.624738236],"iteration":93,"passed_time":0.1297384874,"remaining_time":0.00828118005},
{"learn":[4.612798287],"iteration":94,"passed_time":0.1311984169,"remaining_time":0.006905179835},
{"learn":[4.605222001],"iteration":95,"passed_time":0.1325894164,"remaining_time":0.005524559016},
{"learn":[4.601725912],"iteration":96,"passed_time":0.1340858572,"remaining_time":0.004146985273},
{"learn":[4.59722371],"iteration":97,"passed_time":0.1355027708,"remaining_time":0.00276536267},
{"learn":[4.580235665],"iteration":98,"passed_time":0.1369801055,"remaining_time":0.001383637429},
{"learn":[4.57591791],"iteration":99,"passed_time":0.1383806442,"remaining_time":0}
]}